.coveragerc
.travis.yml
AUTHORS
ChangeLog
HISTORY.rst
LICENSE
README.rst
setup.cfg
setup.py
docs/Makefile
docs/beaglebone.md
docs/make.bat
docs/source/conf.py
docs/source/index.rst
docs/source/_static/imgs/TMP36-pinout.png
docs/source/_static/imgs/bb.jpg
docs/source/_static/imgs/boardie_systemchart.png
docs/source/_static/imgs/cds.jpg
docs/source/_static/imgs/celery_tasks.png
docs/source/_static/imgs/celery_workers.png
docs/source/_static/imgs/dht11.jpg
docs/source/_static/imgs/dht2302.jpg
docs/source/_static/imgs/graphite_dashboard.png
docs/source/_static/imgs/hklab_2013_0.jpg
docs/source/_static/imgs/hklab_2013_1.jpg
docs/source/_static/imgs/hygro.JPG
docs/source/_static/imgs/liquid_flow.jpg
docs/source/_static/imgs/liquid_flow_1.jpg
docs/source/_static/imgs/pinout-beaglebone.png
docs/source/_static/imgs/pinout-raspberry-pi.jpg
docs/source/_static/imgs/real_1.jpg
docs/source/_static/imgs/relay_board.jpg
docs/source/_static/imgs/rpi.jpg
docs/source/_static/imgs/show_me.gif
docs/source/_static/imgs/sispm.jpg
docs/source/_static/imgs/tls.jpg
docs/source/_static/imgs/tmp36.jpg
docs/source/_static/imgs/udoo.jpg
docs/source/api/actions.rst
docs/source/api/installation.rst
docs/source/api/usage.rst
docs/source/config/environment.rst
docs/source/config/supervisor.rst
docs/source/config/worker.rst
docs/source/contrib/contributors.rst
docs/source/contrib/git.rst
docs/source/contrib/new_device.rst
docs/source/hardware/bb.rst
docs/source/hardware/cds.rst
docs/source/hardware/current_sensor.rst
docs/source/hardware/dht.rst
docs/source/hardware/hygro.rst
docs/source/hardware/liquid_flow.rst
docs/source/hardware/pi.rst
docs/source/hardware/relay.rst
docs/source/hardware/sispm.rst
docs/source/hardware/tls.rst
docs/source/hardware/tmp36.rst
docs/source/hardware/udoo.rst
docs/source/hardware/datasheet/current_sensor.pdf
docs/source/hardware/img/current_sensor.jpg
docs/source/hardware/img/dht-humidity-sensing-on-raspberry-pi-with-gdocs-logging.pdf
robotice.egg-info/PKG-INFO
robotice.egg-info/SOURCES.txt
robotice.egg-info/dependency_links.txt
robotice.egg-info/entry_points.txt
robotice.egg-info/not-zip-safe
robotice.egg-info/pbr.json
robotice.egg-info/requires.txt
robotice.egg-info/top_level.txt
